pysmooth-1.5.0.dist-info/METADATA
pysmooth-1.5.0.dist-info/WHEEL
pysmooth-1.5.0.dist-info/entry_points.txt
pysmooth-1.5.0.dist-info/licenses/LICENSE.rst
pysmooth/__init__.py
pysmooth/__main__.py
pysmooth/_smooth.py
pysmooth/py.typed
pysmooth-1.5.0.dist-info/RECORD
