Metadata-Version: 2.1
Name: pysmooth
Version: 1.5.0
Summary: Pysmooth: a Python implementation of R's stats::smooth Tukey's (running median) smoother
Author-Email: Miles Smith <mileschristiansmith@gmail.com>
License: GPL-3.0
Classifier: Development Status :: 4 - Beta
Project-URL: Changelog, https://github.com/milescsmith/pysmooth/releases
Project-URL: homepage, https://github.com/milescsmith/pysmooth
Project-URL: repository, https://github.com/milescsmith/pysmooth
Project-URL: documentation, https://pysmooth.readthedocs.io
Requires-Python: <4.0,>=3.10
Requires-Dist: numpy>=1.26
